hackmatch/__main__.py
hackmatch/ai.py
hackmatch/config.py
hackmatch/game.py
hackmatch/gui.py
hackmatch/main.py
hackmatch/py.typed
hackmatch/util.py
hackmatch-1.3.dist-info/LICENSE
hackmatch-1.3.dist-info/METADATA
hackmatch-1.3.dist-info/WHEEL
hackmatch-1.3.dist-info/entry_points.txt
hackmatch-1.3.dist-info/top_level.txt
hackmatch-1.3.dist-info/RECORD
