Metadata-Version: 2.1
Name: hackmatch
Version: 1.3
Summary: Exapunks HACK*MATCH Bot
Author-email: "Rodrigo Silva (MestreLion)" <linux@rodrigosilva.com>
License: GPL-3.0-or-later
Project-URL: Homepage, https://github.com/MestreLion/hackmatch
Project-URL: Source Code, https://github.com/MestreLion/hackmatch
Project-URL: Issue Tracker, https://github.com/MestreLion/hackmatch/issues
Keywords: exapunks,hackmatch,game,bot
Classifier: Development Status :: 5 - Production/Stable
Classifier: Intended Audience :: End Users/Desktop
Classifier: License :: OSI Approved :: GNU General Public License v3 or later (GPLv3+)
Classifier: Natural Language :: English
Classifier: Operating System :: OS Independent
Classifier: Programming Language :: Python
Classifier: Programming Language :: Python :: 3
Classifier: Programming Language :: Python :: 3.7
Classifier: Programming Language :: Python :: 3.8
Classifier: Programming Language :: Python :: 3.9
Classifier: Programming Language :: Python :: 3.10
Classifier: Programming Language :: Python :: 3.11
Classifier: Programming Language :: Python :: 3.12
Classifier: Topic :: Games/Entertainment :: Arcade
Classifier: Topic :: Games/Entertainment :: Puzzle Games
Classifier: Topic :: Multimedia :: Graphics
Classifier: Topic :: Scientific/Engineering :: Artificial Intelligence
Classifier: Topic :: Scientific/Engineering :: Image Recognition
Requires-Python: >=3.7
License-File: LICENSE
Requires-Dist: Pillow
Requires-Dist: PyAutoGUI
Requires-Dist: PyWinCtl ==0.0.43
Requires-Dist: typing-extensions ; python_version < "3.10"
Provides-Extra: dev
Requires-Dist: black ; extra == 'dev'
Requires-Dist: mypy >=0.900 ; extra == 'dev'
Requires-Dist: types-Pillow ; extra == 'dev'
Requires-Dist: types-PyAutoGUI >0.9.3.2 ; extra == 'dev'
Provides-Extra: extra
Requires-Dist: pygame ; extra == 'extra'
